[{"URI": "http://dbpedia.org/resource/Monty_Python", "support": 2010, "types": "Wikidata:Q43229,Wikidata:Q24229398,DUL:SocialPerson,DUL:Agent,Schema:Organization,DBpedia:Organisation,DBpedia:Group,DBpedia:Agent,DBpedia:ComedyGroup", "surfaceForm": "Python", "offset": 190, "similarityScore": 0.9141249134414391, "percentageOfSecondRank": 0.09153423325252823}, {"URI": "http://dbpedia.org/resource/Resource_Description_Framework", "support": 910, "types": "", "surfaceForm": "RDF", "offset": 208, "similarityScore": 1.0, "percentageOfSecondRank": 1.0230049108140555e-15}, {"URI": "http://dbpedia.org/resource/Resource_Description_Framework", "support": 910, "types": "", "surfaceForm": "RDF", "offset": 327, "similarityScore": 1.0, "percentageOfSecondRank": 1.0230049108140555e-15}, {"URI": "http://dbpedia.org/resource/Resource_Description_Framework", "support": 910, "types": "", "surfaceForm": "RDF", "offset": 890, "similarityScore": 1.0, "percentageOfSecondRank": 1.0230049108140555e-15}, {"URI": "http://dbpedia.org/resource/JSON-LD", "support": 40, "types": "", "surfaceForm": "JSON-LD", "offset": 983, "similarityScore": 1.0, "percentageOfSecondRank": 0.0}, {"URI": "http://dbpedia.org/resource/XML", "support": 8119, "types": "", "surfaceForm": "RDF/XML", "offset": 995, "similarityScore": 1.0, "percentageOfSecondRank": 0.0}, {"URI": "http://dbpedia.org/resource/Resource_Description_Framework", "support": 910, "types": "", "surfaceForm": "RDF", "offset": 1084, "similarityScore": 1.0, "percentageOfSecondRank": 1.0230049108140555e-15}, {"URI": "http://dbpedia.org/resource/XML", "support": 8119, "types": "", "surfaceForm": "RDF/XML", "offset": 1112, "similarityScore": 1.0, "percentageOfSecondRank": 0.0}, {"URI": "http://dbpedia.org/resource/Resource_Description_Framework", "support": 910, "types": "", "surfaceForm": "RDF", "offset": 1272, "similarityScore": 1.0, "percentageOfSecondRank": 1.0230049108140555e-15}, {"URI": "http://dbpedia.org/resource/XML", "support": 8119, "types": "", "surfaceForm": "RDF/XML", "offset": 1296, "similarityScore": 1.0, "percentageOfSecondRank": 0.0}, {"URI": "http://dbpedia.org/resource/RDF_Schema", "support": 69, "types": "", "surfaceForm": "rdfs", "offset": 1390, "similarityScore": 1.0, "percentageOfSecondRank": 0.0}, {"URI": "http://dbpedia.org/resource/RDF_Schema", "support": 69, "types": "", "surfaceForm": "RDF Schema", "offset": 1397, "similarityScore": 1.0, "percentageOfSecondRank": 0.0}, {"URI": "http://dbpedia.org/resource/RDF_Schema", "support": 69, "types": "", "surfaceForm": "RDFS", "offset": 1467, "similarityScore": 1.0, "percentageOfSecondRank": 0.0}, {"URI": "http://dbpedia.org/resource/Resource_Description_Framework", "support": 910, "types": "", "surfaceForm": "RDF", "offset": 1530, "similarityScore": 1.0, "percentageOfSecondRank": 1.0230049108140555e-15}, {"URI": "http://dbpedia.org/resource/Java_virtual_machine", "support": 874, "types": "", "surfaceForm": "Java", "offset": 1652, "similarityScore": 0.9999999999997726, "percentageOfSecondRank": 1.2293137086090605e-13}, {"URI": "http://dbpedia.org/resource/Apache_HTTP_Server", "support": 818, "types": "Wikidata:Q7397,Wikidata:Q386724,Schema:CreativeWork,DBpedia:Work,DBpedia:Software", "surfaceForm": "Apache", "offset": 1660, "similarityScore": 0.9999999936785571, "percentageOfSecondRank": 6.321496576552016e-09}, {"URI": "http://dbpedia.org/resource/Apache_Jena", "support": 19, "types": "Wikidata:Q7397,Wikidata:Q386724,Schema:CreativeWork,DBpedia:Work,DBpedia:Software", "surfaceForm": "Jena", "offset": 1667, "similarityScore": 0.9998275685530199, "percentageOfSecondRank": 0.00016298414700794366}, {"URI": "http://dbpedia.org/resource/Monty_Python", "support": 2010, "types": "Wikidata:Q43229,Wikidata:Q24229398,DUL:SocialPerson,DUL:Agent,Schema:Organization,DBpedia:Organisation,DBpedia:Group,DBpedia:Agent,DBpedia:ComedyGroup", "surfaceForm": "Python", "offset": 1707, "similarityScore": 0.9141249134414391, "percentageOfSecondRank": 0.09153423325252823}, {"URI": "http://dbpedia.org/resource/N-Triples", "support": 26, "types": "", "surfaceForm": "N-Triples", "offset": 1902, "similarityScore": 1.0, "percentageOfSecondRank": 0.0}, {"URI": "http://dbpedia.org/resource/Resource_Description_Framework", "support": 910, "types": "", "surfaceForm": "RDF", "offset": 2085, "similarityScore": 1.0, "percentageOfSecondRank": 1.0230049108140555e-15}, {"URI": "http://dbpedia.org/resource/Resource_Description_Framework", "support": 910, "types": "", "surfaceForm": "RDF", "offset": 2099, "similarityScore": 1.0, "percentageOfSecondRank": 1.0230049108140555e-15}, {"URI": "http://dbpedia.org/resource/SPARQL", "support": 260, "types": "Wikidata:Q9143,Wikidata:Q315,Schema:Language,DBpedia:Language,DBpedia:ProgrammingLanguage", "surfaceForm": "SPARQL", "offset": 2132, "similarityScore": 1.0, "percentageOfSecondRank": 0.0}, {"URI": "http://dbpedia.org/resource/Intelligent_agent", "support": 427, "types": "", "surfaceForm": "intelligent agent", "offset": 2288, "similarityScore": 1.0, "percentageOfSecondRank": 5.756785283234939e-22}, {"URI": "http://dbpedia.org/resource/Concordia_University", "support": 2041, "types": "", "surfaceForm": "Concordia", "offset": 2557, "similarityScore": 0.9999989096251316, "percentageOfSecondRank": 1.0903663691683436e-06}, {"URI": "http://dbpedia.org/resource/Resource_Description_Framework", "support": 910, "types": "", "surfaceForm": "RDF", "offset": 2874, "similarityScore": 1.0, "percentageOfSecondRank": 1.0230049108140555e-15}]